pyspde/__init__.py
pyspde/anisotropy.py
pyspde/grid.py
pyspde/neighbours.py
pyspde/spde.py
pyspde/utils.py
pyspde-0.0.6.dist-info/LICENSE
pyspde-0.0.6.dist-info/METADATA
pyspde-0.0.6.dist-info/WHEEL
pyspde-0.0.6.dist-info/top_level.txt
pyspde-0.0.6.dist-info/RECORD
