Metadata-Version: 2.1
Name: pyspde
Version: 0.0.6
Summary: PySPDE is a Python library for performing simulations and kriging of non-stationary spatial gaussian random fields with Matérn covariance, by solving the following Stochastic Partial Differential Equations (SPDEs)
Author-email: Esteban Jimenez <ejimenez@minerai.com.au>
Project-URL: Homepage, https://github.com/M1nerAI/pyspde
Project-URL: Issues, https://github.com/M1nerAI/pyspde/issues
Classifier: Programming Language :: Python :: 3
Classifier: License :: OSI Approved :: MIT License
Classifier: Operating System :: OS Independent
Requires-Python: >=3.11
License-File: LICENSE
Requires-Dist: scipy
Requires-Dist: numpy
Requires-Dist: matplotlib
Requires-Dist: scikit-sparse ==0.4.12
